{
  "migrations": [
    {
      "version": "14.5.1-beta.0",
      "cli": "nx",
      "description": "Add target update for expo projects in project.json",
      "factory": "./src/migrations/update-14-5-1/add-eas-update-target",
      "package": "@nrwl/expo",
      "name": "add-update-target-14-5-1"
    },
    {
      "version": "15.0.3-beta.0",
      "cli": "nx",
      "description": "Change jest config preset tof expo projects",
      "factory": "./src/migrations/update-15-0-3/change-jest-preset",
      "package": "@nrwl/expo",
      "name": "change-expo-jest-preset"
    },
    {
      "version": "15.0.3-beta.0",
      "cli": "nx",
      "description": "Add targets for @expo/cli and replace eject target",
      "factory": "./src/migrations/update-15-0-3/add-new-expo-cli-targets",
      "package": "@nrwl/expo",
      "name": "add-new-expo-cli-targets"
    }
  ]
}
